Tensorflow24GuanfangJiaochengHeZhinan/README.md
Tensorflow24GuanfangJiaochengHeZhinan/__init__.py
Tensorflow24GuanfangJiaochengHeZhinan/__main__.py
Tensorflow24GuanfangJiaochengHeZhinan/file.epub
Tensorflow24GuanfangJiaochengHeZhinan/index.html
Tensorflow24GuanfangJiaochengHeZhinan/css/__init__.py
Tensorflow24GuanfangJiaochengHeZhinan/css/annotations.css
Tensorflow24GuanfangJiaochengHeZhinan/css/main.css
Tensorflow24GuanfangJiaochengHeZhinan/css/normalize.css
Tensorflow24GuanfangJiaochengHeZhinan/css/popup.css
Tensorflow24GuanfangJiaochengHeZhinan/font/__init__.py
Tensorflow24GuanfangJiaochengHeZhinan/font/fontello.eot
Tensorflow24GuanfangJiaochengHeZhinan/font/fontello.svg
Tensorflow24GuanfangJiaochengHeZhinan/font/fontello.ttf
Tensorflow24GuanfangJiaochengHeZhinan/font/fontello.woff
Tensorflow24GuanfangJiaochengHeZhinan/img/__init__.py
Tensorflow24GuanfangJiaochengHeZhinan/img/annotator-glyph-sprite.png
Tensorflow24GuanfangJiaochengHeZhinan/img/annotator-icon-sprite.png
Tensorflow24GuanfangJiaochengHeZhinan/img/apple-touch-icon.png
Tensorflow24GuanfangJiaochengHeZhinan/img/cancelfullscreen.png
Tensorflow24GuanfangJiaochengHeZhinan/img/close.png
Tensorflow24GuanfangJiaochengHeZhinan/img/fullscreen.png
Tensorflow24GuanfangJiaochengHeZhinan/img/loader.gif
Tensorflow24GuanfangJiaochengHeZhinan/img/menu-icon.png
Tensorflow24GuanfangJiaochengHeZhinan/img/save.png
Tensorflow24GuanfangJiaochengHeZhinan/img/saved.png
Tensorflow24GuanfangJiaochengHeZhinan/img/settings-s.png
Tensorflow24GuanfangJiaochengHeZhinan/img/settings.png
Tensorflow24GuanfangJiaochengHeZhinan/img/star.png
Tensorflow24GuanfangJiaochengHeZhinan/js/__init__.py
Tensorflow24GuanfangJiaochengHeZhinan/js/epub.js
Tensorflow24GuanfangJiaochengHeZhinan/js/epub.min.js
Tensorflow24GuanfangJiaochengHeZhinan/js/epub.min.map
Tensorflow24GuanfangJiaochengHeZhinan/js/hooks.min.js
Tensorflow24GuanfangJiaochengHeZhinan/js/hooks.min.map
Tensorflow24GuanfangJiaochengHeZhinan/js/reader.js
tensorflow_2_4_guanfang_jiaocheng_he_zhinan-2024.3.5.0.dist-info/METADATA
tensorflow_2_4_guanfang_jiaocheng_he_zhinan-2024.3.5.0.dist-info/WHEEL
tensorflow_2_4_guanfang_jiaocheng_he_zhinan-2024.3.5.0.dist-info/entry_points.txt
tensorflow_2_4_guanfang_jiaocheng_he_zhinan-2024.3.5.0.dist-info/top_level.txt
tensorflow_2_4_guanfang_jiaocheng_he_zhinan-2024.3.5.0.dist-info/RECORD
